pydantic_invoices/__init__.py
pydantic_invoices/py.typed
pydantic_invoices/interfaces/__init__.py
pydantic_invoices/interfaces/base.py
pydantic_invoices/interfaces/client_repo.py
pydantic_invoices/interfaces/company_repo.py
pydantic_invoices/interfaces/invoice_repo.py
pydantic_invoices/interfaces/payment_note_repo.py
pydantic_invoices/interfaces/payment_repo.py
pydantic_invoices/interfaces/product_repo.py
pydantic_invoices/schemas/__init__.py
pydantic_invoices/schemas/audit_log.py
pydantic_invoices/schemas/client.py
pydantic_invoices/schemas/company.py
pydantic_invoices/schemas/invoice.py
pydantic_invoices/schemas/invoice_line.py
pydantic_invoices/schemas/payment.py
pydantic_invoices/schemas/payment_note.py
pydantic_invoices/schemas/product.py
pydantic_invoices-1.3.1.dist-info/METADATA
pydantic_invoices-1.3.1.dist-info/WHEEL
pydantic_invoices-1.3.1.dist-info/licenses/LICENSE
pydantic_invoices-1.3.1.dist-info/RECORD
