Metadata-Version: 2.4
Name: pydantic-invoices
Version: 1.3.1
Summary: Pydantic schemas and repository interfaces for invoice management
Project-URL: Homepage, https://github.com/romamo/pydantic-invoices
Project-URL: Repository, https://github.com/romamo/pydantic-invoices
Project-URL: Issues, https://github.com/romamo/pydantic-invoices/issues
Author-email: Roman <pipy@romavm.dev>
License: MIT
License-File: LICENSE
Keywords: billing,invoice,pydantic,repository-pattern,schemas
Classifier: Development Status :: 5 - Production/Stable
Classifier: Intended Audience :: Developers
Classifier: License :: OSI Approved :: MIT License
Classifier: Programming Language :: Python :: 3
Classifier: Programming Language :: Python :: 3.10
Classifier: Programming Language :: Python :: 3.11
Classifier: Programming Language :: Python :: 3.12
Classifier: Programming Language :: Python :: 3.13
Classifier: Topic :: Software Development :: Libraries :: Python Modules
Classifier: Typing :: Typed
Requires-Python: >=3.10
Requires-Dist: pydantic>=2.0.0
Provides-Extra: dev
Requires-Dist: mypy>=1.0.0; extra == 'dev'
Requires-Dist: pytest-cov>=4.0.0; extra == 'dev'
Requires-Dist: pytest>=7.0.0; extra == 'dev'
